{
    "schema":  "OneRouteUpdate.v1",
    "release":  "0.8.6.8",
    "android":  {
                    "versionName":  "0.8.6.8",
                    "versionCode":  62,
                    "asset":  "OneRoute.apk",
                    "apkUrl":  "https://github.com/kolyadkl/oneroute-updates/releases/latest/download/OneRoute.apk",
                    "sha256":  "1a49b402d2730f86d8e96fce42f32d595dc55b9778602e15b5cc076264f8a776",
                    "sizeBytes":  8584450,
                    "notes":  [
                                  "OneRoute 0.8.6.8 - GitHub Updates Release Flow / APK Update Polish"
                              ]
                }
}