{
    "schema":  "OneRouteUpdate.v1",
    "release":  "0.8.55.0",
    "android":  {
                    "versionName":  "0.8.55.0",
                    "versionCode":  153,
                    "asset":  "OneRoute.apk",
                    "apkUrl":  "https://github.com/kolyadkl/oneroute-updates/releases/latest/download/OneRoute.apk",
                    "sha256":  "a33452c760bb43fd2609716b4305085074fa58c20146cbfc882ce9f58bb96b44",
                    "sizeBytes":  48830202,
                    "notes":  [
                                  "OneRoute 0.8.55.0 - VLESS Real FD JNI Sentinel Call / Java FD Close Proof"
                              ]
                }
}